PushedPy/__init__.py
PushedPy-0.0.2.dist-info/LICENSE
PushedPy-0.0.2.dist-info/METADATA
PushedPy-0.0.2.dist-info/WHEEL
PushedPy-0.0.2.dist-info/top_level.txt
PushedPy-0.0.2.dist-info/RECORD
