Metadata-Version: 2.1
Name: PushedPy
Version: 0.0.2
Summary: A Python wrapper for the Pushed.co API
Home-page: https://github.com/mickras/PushedPy
Author: Mick Rasmussen
Author-email: mira19@guldborgsund.dk
License: UNKNOWN
Platform: UNKNOWN
Classifier: Programming Language :: Python :: 3
Classifier: License :: OSI Approved :: MIT License
Classifier: Operating System :: OS Independent
Requires-Python: >=3.6
